odoo8_addon_social_media_pinterest-8.0.1.0.0-py2.7-nspkg.pth
odoo8_addon_social_media_pinterest-8.0.1.0.0.dist-info/DESCRIPTION.rst
odoo8_addon_social_media_pinterest-8.0.1.0.0.dist-info/METADATA
odoo8_addon_social_media_pinterest-8.0.1.0.0.dist-info/RECORD
odoo8_addon_social_media_pinterest-8.0.1.0.0.dist-info/WHEEL
odoo8_addon_social_media_pinterest-8.0.1.0.0.dist-info/metadata.json
odoo8_addon_social_media_pinterest-8.0.1.0.0.dist-info/namespace_packages.txt
odoo8_addon_social_media_pinterest-8.0.1.0.0.dist-info/top_level.txt
odoo_addons/social_media_pinterest/README.rst
odoo_addons/social_media_pinterest/__init__.py
odoo_addons/social_media_pinterest/__openerp__.py
odoo_addons/social_media_pinterest/models/__init__.py
odoo_addons/social_media_pinterest/models/res_config.py
odoo_addons/social_media_pinterest/models/website.py
odoo_addons/social_media_pinterest/static/description/icon.png
odoo_addons/social_media_pinterest/static/description/index.html
odoo_addons/social_media_pinterest/static/description/pinterest.png
odoo_addons/social_media_pinterest/static/description/settings.png
odoo_addons/social_media_pinterest/views/res_config.xml
odoo_addons/social_media_pinterest/views/website_templates.xml
odoo_addons/social_media_pinterest/views/website_views.xml
